faker_optional/__init__.py
faker_optional/model.py
faker_optional/py.typed
faker_optional/version.py
faker_optional-0.1.1.dist-info/LICENSE
faker_optional-0.1.1.dist-info/METADATA
faker_optional-0.1.1.dist-info/WHEEL
faker_optional-0.1.1.dist-info/top_level.txt
faker_optional-0.1.1.dist-info/RECORD
