Metadata-Version: 2.1
Name: faker-optional
Version: 0.1.1
Summary: ('Wrapper over other Faker providers to return their value or `None`. Useful to create data of type `Optional[Any]`.',)
Home-page: https://github.com/lyz-code/faker-optional
Author: Lyz
Author-email: lyz-code-security-advisories@riseup.net
License: GNU General Public License v3
Platform: UNKNOWN
Classifier: Development Status :: 2 - Pre-Alpha
Classifier: Intended Audience :: Developers
Classifier: License :: OSI Approved :: GNU General Public License v3 or later (GPLv3+)
Classifier: Operating System :: Unix
Classifier: Operating System :: POSIX
Classifier: Programming Language :: Python
Classifier: Programming Language :: Python :: 3
Classifier: Programming Language :: Python :: 3.6
Classifier: Programming Language :: Python :: 3.7
Classifier: Programming Language :: Python :: 3.8
Classifier: Topic :: Utilities
Classifier: Natural Language :: English
Requires-Python: >=3.6
License-File: LICENSE
Requires-Dist: faker
